{
	"m_Commander":"Tychus",
	"m_Language":"ChineseSimplified",
	"m_Level":6,
	"m_Masteries":[
		0,
		30,
		15,
		15,
		0,
		30
	],
	"m_Prestige":0,
	"m_Title":"练级双BE",
	"m_Desc":"首发天狼星增加容若率，后续英雄看因子、AI、地图\n优先升级防御\n不法之徒科技自行选择",
	"m_EventModels":[
		{"m_UnitIDList":[483178260,483178260,483178260,483178260],"m_Guid":"58048155-aa27-413e-83ea-d1dc3151fa75","m_StartTime":1,"m_TriggerTime":54,"m_EndTime":60,"m_Hide":false,"class":"Game.Model.PlayerOperatorEventModel"},
		{"m_UnitIDList":[2091357797],"m_Guid":"679cb10c-7b89-4741-b897-365ee3a30215","m_StartTime":45,"m_TriggerTime":53,"m_EndTime":59,"m_Hide":false,"class":"Game.Model.PlayerOperatorEventModel"},
		{"m_UnitIDList":[483178260,483178260,483178260,483178260],"m_Guid":"fd5a0cfa-bb5d-443d-bd81-77356e57421f","m_StartTime":64,"m_TriggerTime":110,"m_EndTime":115,"m_Hide":false,"class":"Game.Model.PlayerOperatorEventModel"},
		{"m_UnitIDList":[1412206016],"m_Guid":"348655be-364e-4b32-8ba9-7e8d48954a28","m_StartTime":95,"m_TriggerTime":105,"m_EndTime":110,"m_Hide":false,"class":"Game.Model.PlayerOperatorEventModel"},
		{"m_UnitIDList":[2068615341],"m_Guid":"8b3e4441-adb3-4e00-8823-d4bf0cc95a84","m_StartTime":111,"m_TriggerTime":130,"m_EndTime":140,"m_Hide":false,"class":"Game.Model.PlayerOperatorEventModel"},
		{"m_UnitIDList":[483178260,483178260,483178260,483178260],"m_Guid":"5eb93690-1089-45f9-81b0-14cd6fd7d88f","m_StartTime":130,"m_TriggerTime":140,"m_EndTime":145,"m_Hide":false,"class":"Game.Model.PlayerOperatorEventModel"},
		{"m_TechnologyIDList":[545256047],"m_Guid":"df6d3d87-e908-472d-882d-4d5c7ac86272","m_StartTime":131,"m_TriggerTime":141,"m_EndTime":147,"m_Hide":false,"class":"Game.Model.PlayerTechnologyEventModel"},
		{"m_UnitIDList":[2091357797],"m_Guid":"bbefe5c0-eacb-4233-a1d9-1fb668cc7118","m_StartTime":137,"m_TriggerTime":144,"m_EndTime":150,"m_Hide":false,"class":"Game.Model.PlayerOperatorEventModel"},
		{"m_UnitIDList":[2032790596],"m_Guid":"91a91ae2-d7d2-4e35-9db9-f5c419126118","m_StartTime":180,"m_TriggerTime":190,"m_EndTime":195,"m_Hide":false,"class":"Game.Model.PlayerOperatorEventModel"},
		{"m_UnitIDList":[483178260,483178260],"m_Guid":"f4fc9d79-a4d9-4d22-9090-81261a802684","m_StartTime":195,"m_TriggerTime":220,"m_EndTime":225,"m_Hide":false,"class":"Game.Model.PlayerOperatorEventModel"},
		{"m_UnitIDList":[1626286454,1412206016],"m_Guid":"d6e1a411-f127-4def-805d-5d7bc221c225","m_StartTime":215,"m_TriggerTime":225,"m_EndTime":230,"m_Hide":false,"class":"Game.Model.PlayerOperatorEventModel"},
		{"m_UnitIDList":[483178260,483178260],"m_Guid":"0766a5bd-1358-442a-a7db-51a7379b6ca5","m_StartTime":231,"m_TriggerTime":240,"m_EndTime":245,"m_Hide":false,"class":"Game.Model.PlayerOperatorEventModel"},
		{"m_TechnologyIDList":[813960562,555384031],"m_Guid":"8f1a21e2-d3d9-4ac5-a2a6-087197a42254","m_StartTime":270,"m_TriggerTime":287,"m_EndTime":294,"m_Hide":false,"class":"Game.Model.PlayerTechnologyEventModel"},
		{"m_UnitIDList":[483178260,483178260,483178260,483178260],"m_Guid":"6c9f1a12-eecb-4816-8f60-adad3cc8849c","m_StartTime":250,"m_TriggerTime":280,"m_EndTime":285,"m_Hide":false,"class":"Game.Model.PlayerOperatorEventModel"},
		{"m_UnitIDList":[483178260,483178260,483178260,483178260],"m_Guid":"500141d7-8d8b-47e2-a77f-b0c2b2beca42","m_StartTime":290,"m_TriggerTime":320,"m_EndTime":325,"m_Hide":false,"class":"Game.Model.PlayerOperatorEventModel"},
		{"m_UnitIDList":[483178260,483178260,483178260,483178260],"m_Guid":"bd853488-03b9-4f13-acef-903c61e14769","m_StartTime":340,"m_TriggerTime":360,"m_EndTime":365,"m_Hide":false,"class":"Game.Model.PlayerOperatorEventModel"},
		{"m_TechnologyIDList":[1940131797,2034521205],"m_Guid":"eb92645a-ced1-4137-b55c-181b3895a64f","m_StartTime":375,"m_TriggerTime":390,"m_EndTime":400,"m_Hide":false,"class":"Game.Model.PlayerTechnologyEventModel"},
		{"m_UnitIDList":[1981350079,852303631],"m_Guid":"d7ef3f10-c524-45e9-8baf-323ba605fa9f","m_StartTime":390,"m_TriggerTime":405,"m_EndTime":415,"m_Hide":false,"class":"Game.Model.PlayerOperatorEventModel"},
		{"m_TechnologyIDList":[1053231280],"m_Guid":"c2267b79-6aa2-4c08-ac87-aad92c294b6c","m_StartTime":430,"m_TriggerTime":445,"m_EndTime":458,"m_Hide":false,"class":"Game.Model.PlayerTechnologyEventModel"},
		{"m_UnitIDList":[922589071],"m_Guid":"0a14e449-a4a0-461d-b520-c2b5becc8320","m_StartTime":523,"m_TriggerTime":535,"m_EndTime":545,"m_Hide":false,"class":"Game.Model.PlayerOperatorEventModel"},
		{"m_TechnologyIDList":[1483577089],"m_Guid":"76cfe398-42f0-491c-b316-7422cc548790","m_StartTime":530,"m_TriggerTime":545,"m_EndTime":552,"m_Hide":false,"class":"Game.Model.PlayerTechnologyEventModel"},
		{"m_UnitIDList":[378335540],"m_Guid":"5528f266-ecf6-4418-887c-8a4d5154c0e5","m_StartTime":575,"m_TriggerTime":590,"m_EndTime":600,"m_Hide":false,"class":"Game.Model.PlayerOperatorEventModel"},
		{"m_TechnologyIDList":[27526007],"m_Guid":"2431903e-dd30-4978-bdf9-0a1ff27d4f6c","m_StartTime":700,"m_TriggerTime":715,"m_EndTime":730,"m_Hide":false,"class":"Game.Model.PlayerTechnologyEventModel"}
	],
	"m_Guid":"11cc2a5b-40f6-43bf-aba2-511068f19417",
	"m_DemoURL":""
}